[
  {
    "titulo": "Serie A: Bologna vs Cagliari",
    "categoria": "futbol",
    "clase": "IT",
    "fecha": "Domingo 03 de Mayo 2026",
    "fecha_iso": "2026-05-03",
    "hora": "05:30",
    "duracion_min": 140,
    "canales": [
      {
        "nombre": "Espn",
        "calidad": "720p",
        "url": "https://streamhdx.com/live1.php?stream=espn"
      },
      {
        "nombre": "Fox Deportes USA",
        "calidad": "720p",
        "url": "https://streamhdx.com/live1.php?stream=fox_deportes_usa"
      },
      {
        "nombre": "Espn MX",
        "calidad": "720p",
        "url": "https://streamhdx.com/live1.php?stream=espnmx"
      }
    ]
  },
  {
    "titulo": "LaLiga: Celta de Vigo vs Elche",
    "categoria": "futbol",
    "clase": "ES",
    "fecha": "Domingo 03 de Mayo 2026",
    "fecha_iso": "2026-05-03",
    "hora": "07:00",
    "duracion_min": 140,
    "canales": [
      {
        "nombre": "Espn 2",
        "calidad": "720p",
        "url": "https://streamhdx.com/live1.php?stream=espn2"
      },
      {
        "nombre": "Disney +",
        "calidad": "720p",
        "url": "https://streamhdx.com/live1.php?stream=disney1"
      },
      {
        "nombre": "Espn Deportes",
        "calidad": "720p",
        "url": "https://streamhdx.com/live1.php?stream=espndeportes"
      }
    ]
  },
  {
    "titulo": "Eredivisie: Fortuna Sittard vs Feyenoord",
    "categoria": "futbol",
    "clase": "HOL",
    "fecha": "Domingo 03 de Mayo 2026",
    "fecha_iso": "2026-05-03",
    "hora": "07:30",
    "duracion_min": 140,
    "canales": [
      {
        "nombre": "Espn 2 MX",
        "calidad": "720p",
        "url": "https://streamhdx.com/live1.php?stream=espn2mx"
      },
      {
        "nombre": "Disney +",
        "calidad": "720p",
        "url": "https://streamhdx.com/live1.php?stream=disney2"
      }
    ]
  },
  {
    "titulo": "Primera División: Progreso vs Cerro Largo",
    "categoria": "futbol",
    "clase": "URU",
    "fecha": "Domingo 03 de Mayo 2026",
    "fecha_iso": "2026-05-03",
    "hora": "07:30",
    "duracion_min": 140,
    "canales": [
      {
        "nombre": "Disney +",
        "calidad": "720p",
        "url": "https://streamhdx.com/live1.php?stream=disney3"
      }
    ]
  },
  {
    "titulo": "Copa de Primera: Olimpia vs Sportivo Ameliano",
    "categoria": "futbol",
    "clase": "PY",
    "fecha": "Domingo 03 de Mayo 2026",
    "fecha_iso": "2026-05-03",
    "hora": "07:30",
    "duracion_min": 140,
    "canales": [
      {
        "nombre": "Fanatiz",
        "calidad": "720p",
        "url": "https://streamhdx.com/live1.php?stream=fanatiz1"
      }
    ]
  },
  {
    "titulo": "Copa de Primera: Recoleta vs Cerro Porteño",
    "categoria": "futbol",
    "clase": "PY",
    "fecha": "Domingo 03 de Mayo 2026",
    "fecha_iso": "2026-05-03",
    "hora": "07:30",
    "duracion_min": 140,
    "canales": [
      {
        "nombre": "Fanatiz",
        "calidad": "720p",
        "url": "https://streamhdx.com/live1.php?stream=fanatiz2"
      }
    ]
  },
  {
    "titulo": "Premier League: AFC Bournemouth vs Crystal Palace",
    "categoria": "futbol",
    "clase": "ENG",
    "fecha": "Domingo 03 de Mayo 2026",
    "fecha_iso": "2026-05-03",
    "hora": "08:00",
    "duracion_min": 140,
    "canales": [
      {
        "nombre": "Fox One 1",
        "calidad": "720p",
        "url": "https://streamhdx.com/live1.php?stream=foxone1"
      },
      {
        "nombre": "Peacock TV",
        "calidad": "720p",
        "url": "https://streamhdx.com/live1.php?stream=evento1"
      },
      {
        "nombre": "Disney +",
        "calidad": "720p",
        "url": "https://streamhdx.com/live1.php?stream=disney4"
      }
    ]
  },
  {
    "titulo": "Serie A: Sassuolo vs Milan",
    "categoria": "futbol",
    "clase": "it",
    "fecha": "Domingo 03 de Mayo 2026",
    "fecha_iso": "2026-05-03",
    "hora": "08:00",
    "duracion_min": 140,
    "canales": [
      {
        "nombre": "Espn 3",
        "calidad": "720p",
        "url": "https://streamhdx.com/live1.php?stream=espn3"
      },
      {
        "nombre": "Espn MX",
        "calidad": "720p",
        "url": "https://streamhdx.com/live1.php?stream=espnmx"
      },
      {
        "nombre": "Disney +",
        "calidad": "720p",
        "url": "https://streamhdx.com/live1.php?stream=disney5"
      }
    ]
  },
  {
    "titulo": "Ligue 1: Lille vs Le Havre",
    "categoria": "futbol",
    "clase": "FRA",
    "fecha": "Domingo 03 de Mayo 2026",
    "fecha_iso": "2026-05-03",
    "hora": "08:00",
    "duracion_min": 140,
    "canales": [
      {
        "nombre": "Fox One 2",
        "calidad": "720p",
        "url": "https://streamhdx.com/live1.php?stream=foxone2"
      },
      {
        "nombre": "Disney +",
        "calidad": "720p",
        "url": "https://streamhdx.com/live1.php?stream=disney6"
      }
    ]
  },
  {
    "titulo": "Bundesliga: St. Pauli vs Mainz 05",
    "categoria": "futbol",
    "clase": "ALE",
    "fecha": "Domingo 03 de Mayo 2026",
    "fecha_iso": "2026-05-03",
    "hora": "08:30",
    "duracion_min": 140,
    "canales": [
      {
        "nombre": "Espn 5",
        "calidad": "720p",
        "url": "https://streamhdx.com/live1.php?stream=espn5"
      },
      {
        "nombre": "Disney +",
        "calidad": "720p",
        "url": "https://streamhdx.com/live1.php?stream=disney7"
      }
    ]
  },
  {
    "titulo": "LaLiga: Getafe vs Rayo Vallecano",
    "categoria": "futbol",
    "clase": "ES",
    "fecha": "Domingo 03 de Mayo 2026",
    "fecha_iso": "2026-05-03",
    "hora": "09:15",
    "duracion_min": 140,
    "canales": [
      {
        "nombre": "Espn 2",
        "calidad": "720p",
        "url": "https://streamhdx.com/live1.php?stream=espn2"
      },
      {
        "nombre": "Disney +",
        "calidad": "720p",
        "url": "https://streamhdx.com/live1.php?stream=disney8"
      }
    ]
  },
  {
    "titulo": "UEFA Champions League (F): Barcelona vs. Bayern Munich | Semi - Vuelta",
    "categoria": "futbol",
    "clase": "CHA",
    "fecha": "Domingo 03 de Mayo 2026",
    "fecha_iso": "2026-05-03",
    "hora": "09:20",
    "duracion_min": 140,
    "canales": [
      {
        "nombre": "Espn 5",
        "calidad": "720p",
        "url": "https://streamhdx.com/live1.php?stream=espn5"
      }
    ]
  },
  {
    "titulo": "Premier League: Manchester United vs Liverpool",
    "categoria": "futbol",
    "clase": "ENG",
    "fecha": "Domingo 03 de Mayo 2026",
    "fecha_iso": "2026-05-03",
    "hora": "09:30",
    "duracion_min": 140,
    "canales": [
      {
        "nombre": "Espn",
        "calidad": "720p",
        "url": "https://streamhdx.com/live1.php?stream=espn"
      },
      {
        "nombre": "Telemundo",
        "calidad": "720p",
        "url": "https://streamhdx.com/live1.php?stream=telemundo"
      },
      {
        "nombre": "Peacock TV",
        "calidad": "720p",
        "url": "https://streamhdx.com/live1.php?stream=evento2"
      },
      {
        "nombre": "Max",
        "calidad": "720p",
        "url": "https://streamhdx.com/live1.php?stream=max1"
      },
      {
        "nombre": "Disney +",
        "calidad": "720p",
        "url": "https://streamhdx.com/live1.php?stream=disney9"
      }
    ]
  },
  {
    "titulo": "Eredivisie: AZ vs Twente",
    "categoria": "futbol",
    "clase": "HOL",
    "fecha": "Domingo 03 de Mayo 2026",
    "fecha_iso": "2026-05-03",
    "hora": "09:45",
    "duracion_min": 140,
    "canales": [
      {
        "nombre": "Espn 2 MX",
        "calidad": "720p",
        "url": "https://streamhdx.com/live1.php?stream=espn2mx"
      },
      {
        "nombre": "Disney +",
        "calidad": "720p",
        "url": "https://streamhdx.com/live1.php?stream=disney10"
      }
    ]
  },
  {
    "titulo": "Ligue 1: Paris vs Brest",
    "categoria": "futbol",
    "clase": "FRA",
    "fecha": "Domingo 03 de Mayo 2026",
    "fecha_iso": "2026-05-03",
    "hora": "10:15",
    "duracion_min": 140,
    "canales": [
      {
        "nombre": "Fox One 3",
        "calidad": "720p",
        "url": "https://streamhdx.com/live1.php?stream=foxone3"
      },
      {
        "nombre": "Disney +",
        "calidad": "720p",
        "url": "https://streamhdx.com/live1.php?stream=disney11"
      }
    ]
  },
  {
    "titulo": "Ligue 1: Strasbourg vs Toulouse",
    "categoria": "futbol",
    "clase": "FRA",
    "fecha": "Domingo 03 de Mayo 2026",
    "fecha_iso": "2026-05-03",
    "hora": "10:15",
    "duracion_min": 140,
    "canales": [
      {
        "nombre": "Fox One 4",
        "calidad": "720p",
        "url": "https://streamhdx.com/live1.php?stream=foxone4"
      },
      {
        "nombre": "Disney +",
        "calidad": "720p",
        "url": "https://streamhdx.com/live1.php?stream=disney12"
      }
    ]
  },
  {
    "titulo": "Ligue 1: Auxerre vs Angers SCO",
    "categoria": "futbol",
    "clase": "FRA",
    "fecha": "Domingo 03 de Mayo 2026",
    "fecha_iso": "2026-05-03",
    "hora": "10:15",
    "duracion_min": 140,
    "canales": [
      {
        "nombre": "Fox One 5",
        "calidad": "720p",
        "url": "https://streamhdx.com/live1.php?stream=foxone5"
      },
      {
        "nombre": "Disney +",
        "calidad": "720p",
        "url": "https://streamhdx.com/live1.php?stream=disney13"
      }
    ]
  },
  {
    "titulo": "Bundesliga: Borussia M'gladbach vs Borussia Dortmund",
    "categoria": "futbol",
    "clase": "ale",
    "fecha": "Domingo 03 de Mayo 2026",
    "fecha_iso": "2026-05-03",
    "hora": "10:30",
    "duracion_min": 140,
    "canales": [
      {
        "nombre": "Disney +",
        "calidad": "720p",
        "url": "https://streamhdx.com/live1.php?stream=disney14"
      }
    ]
  },
  {
    "titulo": "Primera División: Boston River vs Central Español",
    "categoria": "futbol",
    "clase": "uru",
    "fecha": "Domingo 03 de Mayo 2026",
    "fecha_iso": "2026-05-03",
    "hora": "10:30",
    "duracion_min": 140,
    "canales": [
      {
        "nombre": "Disney +",
        "calidad": "720p",
        "url": "https://streamhdx.com/live1.php?stream=disney15"
      }
    ]
  },
  {
    "titulo": "Serie A: Juventus vs Verona",
    "categoria": "futbol",
    "clase": "IT",
    "fecha": "Domingo 03 de Mayo 2026",
    "fecha_iso": "2026-05-03",
    "hora": "11:00",
    "duracion_min": 140,
    "canales": [
      {
        "nombre": "Disney +",
        "calidad": "720p",
        "url": "https://streamhdx.com/live1.php?stream=disney16"
      }
    ]
  },
  {
    "titulo": "Liga 1: Sporting Cristal vs Cusco",
    "categoria": "futbol",
    "clase": "PE",
    "fecha": "Domingo 03 de Mayo 2026",
    "fecha_iso": "2026-05-03",
    "hora": "11:00",
    "duracion_min": 140,
    "canales": [
      {
        "nombre": "L1 Max",
        "calidad": "720p",
        "url": "https://streamhdx.com/live1.php?stream=liga1max"
      },
      {
        "nombre": "Fanatiz",
        "calidad": "720p",
        "url": "https://streamhdx.com/live1.php?stream=fanatiz3"
      }
    ]
  },
  {
    "titulo": "F2: Miami Gardens – Carrera",
    "categoria": "futbol",
    "clase": "F2",
    "fecha": "Domingo 03 de Mayo 2026",
    "fecha_iso": "2026-05-03",
    "hora": "11:15",
    "duracion_min": 140,
    "canales": [
      {
        "nombre": "Espn 2",
        "calidad": "720p",
        "url": "https://streamhdx.com/live1.php?stream=espn2"
      }
    ]
  },
  {
    "titulo": "LaLiga: Real Betis vs Real Oviedo",
    "categoria": "futbol",
    "clase": "ES",
    "fecha": "Domingo 03 de Mayo 2026",
    "fecha_iso": "2026-05-03",
    "hora": "11:30",
    "duracion_min": 140,
    "canales": [
      {
        "nombre": "Dsports",
        "calidad": "720p",
        "url": "https://streamhdx.com/live1.php?stream=dsports"
      },
      {
        "nombre": "Espn Deportes",
        "calidad": "720p",
        "url": "https://streamhdx.com/live1.php?stream=espndeportes"
      }
    ]
  },
  {
    "titulo": "Copa de la Liga: Univ. Concepción vs Universidad Católica",
    "categoria": "futbol",
    "clase": "ch",
    "fecha": "Domingo 03 de Mayo 2026",
    "fecha_iso": "2026-05-03",
    "hora": "11:30",
    "duracion_min": 140,
    "canales": [
      {
        "nombre": "MAX",
        "calidad": "720p",
        "url": "https://streamhdx.com/live1.php?stream=max2"
      }
    ]
  }
]